{
    "meta": {
        "date": "24/09/2024",
        "time": "08:18",
        "title": "st_regression_MFILE",
        "commit_message": "Increase lablxc length to 30 \\(#3327\\) ",
        "commit_hash": "566a59a52bc1c5e1b90520555bd4a345a48fa0fc"
    },
    "tracking": {
        "te": 11.793296747022824,
        "rmajor": 4.5,
        "cdirt": 3724.116821864589,
        "pheat": 0.0,
        "fwoth": 0.018000000000000002,
        "vol": 1312.7025860297895,
        "ralpne": 0.08882289284410624,
        "blnkoth": 1.0,
        "vvblgap": 0.01,
        "bootipf": 0.9,
        "n_tf": 12.0,
        "facoh": 1e-10,
        "taueff": 2.55521143008299,
        "fwith": 0.018000000000000002,
        "nesep": 1.2844646943688184e+19,
        "triang": 0.5,
        "dene": 9.70816838913845e+19,
        "powfmw": 2500.000000000015,
        "hfact": 1.2,
        "tesep": 0.125,
        "divlife": 30.0,
        "concost": 5699.079282485352,
        "pnetelmw": 561.103979042919,
        "precomp": 0.0,
        "zeff": 3.6154514823848496,
        "tburn": 1000.0,
        "kappa": 2.8,
        "neped": 1.2844646943688184e+19,
        "wallmw": 2.2686620325500617,
        "powerht": 352.05821162155894,
        "scrapli": 0.1,
        "shldith": 0.3911670956974132,
        "dnitot": 8.361136001056553e+19,
        "bmaxtf": 11.825769377853717,
        "tftsgap": 0.01,
        "teped": 4.5,
        "tfthko": 0.7743028572327634,
        "vstot": -89.0,
        "pdivt": 179.99999999999488,
        "bore": 0.23488719296445132,
        "ne0": 1.9018577735989094e+20,
        "te0": 25.854827982883585,
        "gapoh": 0.0,
        "faccd": 0.07207433096731164,
        "ohcth": 0.20164285410537272,
        "pradmw": 439.5120236113995,
        "q95": 5.830249397419175,
        "beta": 0.1312011863460369,
        "dnz": 1.0149575470476893e+17,
        "pnucblkt": 1409.4584441112945,
        "shldoth": 0.30000000000000004,
        "gapds": 0.01,
        "gapsto": 1.079443444738107,
        "triang95": 0.3333333333333333,
        "rminor": 2.5,
        "sarea": 810.4940458049573,
        "bt": 3.0,
        "kappa95": 2.4999999999999996,
        "pnucshld": 0.44343917708774966,
        "blnkith": 0.0,
        "tfcth": 0.7743028572327634,
        "pinjmw": 143.10867427261843,
        "pinnerzoneradmw": 267.45381198983546,
        "etath": 0.4,
        "pgrossmw": 1259.8829780758028,
        "aspect": 1.8,
        "scraplo": 0.1
    }
}